{
  "version": "7",
  "dialect": "sqlite",
  "entries": [
    {
      "idx": 0,
      "version": "6",
      "when": 1784228633133,
      "tag": "0000_dusty_masque",
      "breakpoints": true
    },
    {
      "idx": 1,
      "version": "6",
      "when": 1784228646864,
      "tag": "0001_seed_categories",
      "breakpoints": true
    },
    {
      "idx": 2,
      "version": "6",
      "when": 1784234337839,
      "tag": "0002_categories_name_nocase",
      "breakpoints": true
    },
    {
      "idx": 3,
      "version": "6",
      "when": 1784332723947,
      "tag": "0003_staged_transactions_drop_bic",
      "breakpoints": true
    },
    {
      "idx": 4,
      "version": "6",
      "when": 1784460274815,
      "tag": "0004_asset_snapshots_nonneg",
      "breakpoints": true
    }
  ]
}